lambdaChaining/__init__.py
lambdaChaining-1.0.0.dist-info/LICENSE
lambdaChaining-1.0.0.dist-info/METADATA
lambdaChaining-1.0.0.dist-info/WHEEL
lambdaChaining-1.0.0.dist-info/top_level.txt
lambdaChaining-1.0.0.dist-info/RECORD
